CHANGELOG.txt
LICENCE.txt
MANIFEST.in
README.md
setup.py
lucapackage/__init__.py
lucapackage.egg-info/PKG-INFO
lucapackage.egg-info/SOURCES.txt
lucapackage.egg-info/dependency_links.txt
lucapackage.egg-info/top_level.txt