Metadata-Version: 2.1
Name: lucapackage
Version: 0.0.1
Summary: A very basic Python Package
Home-page: UNKNOWN
Author: Luca Mezger
Author-email: lucamezger88@gmail.com
License: MIT
Keywords: pythonpackage
Platform: UNKNOWN
Classifier: Development Status :: 5 - Production/Stable
Classifier: Intended Audience :: Education
Classifier: Operating System :: Microsoft :: Windows :: Windows 10
Classifier: License :: OSI Approved :: MIT License
Classifier: Programming Language :: Python :: 3
License-File: LICENCE.txt
